AUTHORS.rst
CONTRIBUTING.rst
HISTORY.rst
LICENSE
MANIFEST.in
README.md
requirements.txt
requirements_dev.txt
setup.cfg
setup.py
docs/Makefile
docs/authors.rst
docs/conf.py
docs/contributing.rst
docs/history.rst
docs/index.rst
docs/installation.rst
docs/make.bat
docs/modules.rst
docs/pyvolume.rst
docs/readme.rst
docs/usage.rst
docs/_build/html/_static/ajax-loader.gif
docs/_build/html/_static/comment-bright.png
docs/_build/html/_static/comment-close.png
docs/_build/html/_static/comment.png
docs/_build/html/_static/down-pressed.png
docs/_build/html/_static/down.png
docs/_build/html/_static/file.png
docs/_build/html/_static/minus.png
docs/_build/html/_static/plus.png
docs/_build/html/_static/up-pressed.png
docs/_build/html/_static/up.png
pyvolume/__init__.py
pyvolume/exceptions.py
pyvolume/local.py
pyvolume/manager.py
pyvolume/sshfs.py
pyvolume/zkfuse.py
pyvolume.egg-info/PKG-INFO
pyvolume.egg-info/SOURCES.txt
pyvolume.egg-info/dependency_links.txt
pyvolume.egg-info/entry_points.txt
pyvolume.egg-info/not-zip-safe
pyvolume.egg-info/requires.txt
pyvolume.egg-info/top_level.txt
tests/__init__.py
tests/test_pyvolume_sshfs.py