Metadata-Version: 1.1
Name: pyvolume
Version: 0.1.2
Summary: Python Docker Volume driver
Home-page: https://github.com/ronin13/pyvolume
Author: Raghavendra Prabhu
Author-email: me@rdprabhu.com
License: MIT license
Keywords: pyvolume
Platform: UNKNOWN
Classifier: Development Status :: 2 - Pre-Alpha
Classifier: Intended Audience :: Developers
Classifier: License :: OSI Approved :: MIT License
Classifier: Natural Language :: English
Classifier: Programming Language :: Python :: 2
Classifier: Programming Language :: Python :: 2.6
Classifier: Programming Language :: Python :: 2.7
Classifier: Programming Language :: Python :: 3
Classifier: Programming Language :: Python :: 3.3
Classifier: Programming Language :: Python :: 3.4
Classifier: Programming Language :: Python :: 3.5
